fxapi/__init__.py
fxapi/client.py
fxapi-1.1.dist-info/METADATA
fxapi-1.1.dist-info/WHEEL
fxapi-1.1.dist-info/top_level.txt
fxapi-1.1.dist-info/RECORD
