Metadata-Version: 2.1
Name: fxapi
Version: 1.1
Summary: FXaPi is a unofficial python module for the site fxp.co.il
Home-page: https://github.com/avramit/FXaPi
Author: Amit Avrahamov
Author-email: avr.amit02@gmail.com
License: UNKNOWN
Platform: UNKNOWN
Requires-Dist: requests
Requires-Dist: lxml
